mindsight_people_control_api/__init__.py
mindsight_people_control_api/helpers/__init__.py
mindsight_people_control_api/helpers/base_requests.py
mindsight_people_control_api/helpers/exceptions.py
mindsight_people_control_api/helpers/models.py
mindsight_people_control_api/scripts/__init__.py
mindsight_people_control_api/scripts/area_records.py
mindsight_people_control_api/scripts/areas.py
mindsight_people_control_api/scripts/branch_corporations.py
mindsight_people_control_api/scripts/corporations.py
mindsight_people_control_api/scripts/employee_areas.py
mindsight_people_control_api/scripts/employee_managers.py
mindsight_people_control_api/scripts/employee_positions.py
mindsight_people_control_api/scripts/employee_records.py
mindsight_people_control_api/scripts/employees.py
mindsight_people_control_api/scripts/parent_areas.py
mindsight_people_control_api/scripts/position_records.py
mindsight_people_control_api/scripts/positions.py
mindsight_people_control_api/scripts/users.py
mindsight_people_control_api/settings.py
mindsight_people_control_api/utils/__init__.py
mindsight_people_control_api/utils/aux_functions.py
mindsight_people_control_api-0.1.21.dist-info/LICENSE
mindsight_people_control_api-0.1.21.dist-info/METADATA
mindsight_people_control_api-0.1.21.dist-info/WHEEL
mindsight_people_control_api-0.1.21.dist-info/RECORD
