Metadata-Version: 2.1
Name: mindsight-people-control-api
Version: 0.1.21
Summary: Mindsight People Control API to create, update and delete records
Home-page: https://github.com/people-analytics-tech/mindsight-people-control-api
License: MIT
Author: stone_people_analytics
Author-email: systems-techpeople@stone.com.br
Maintainer: diogo56
Maintainer-email: diogo.amorim2001@gmail.com
Requires-Python: >=3.9,<4.0
Classifier: License :: OSI Approved :: MIT License
Classifier: Programming Language :: Python :: 3
Classifier: Programming Language :: Python :: 3.9
Classifier: Programming Language :: Python :: 3.10
Classifier: Programming Language :: Python :: 3.11
Classifier: Programming Language :: Python :: 3.12
Requires-Dist: pytest (>=7.4.2,<8.0.0)
Requires-Dist: python-decouple (>=3.8,<4.0)
Requires-Dist: requests (>=2.31.0,<3.0.0)
Project-URL: Repository, https://github.com/people-analytics-tech/mindsight-people-control-api
